[
  {
    "company_name": "Group 42 Holding",
    "brand_name": "G42",
    "slug": "g42-holding",
    "sector": "AI & Technology",
    "sub_sector": "AI Holding Group",
    "hq_city": "Abu Dhabi",
    "hq_country": "UAE",
    "is_g42_group": true,
    "tier": "tier_1",
    "status": "active"
  },
  {
    "company_name": "CPX Holding",
    "brand_name": "CPX",
    "slug": "cpx-holding",
    "sector": "AI Cybersecurity",
    "sub_sector": "Managed Security & Cyber Resilience",
    "hq_city": "Abu Dhabi",
    "hq_country": "UAE",
    "is_g42_group": true,
    "tier": "tier_1",
    "status": "active"
  },
  {
    "company_name": "Core42",
    "brand_name": null,
    "slug": "core42",
    "sector": "AI Infrastructure & Cloud",
    "sub_sector": "Sovereign AI & Enterprise Cloud",
    "hq_city": "Abu Dhabi",
    "hq_country": "UAE",
    "is_g42_group": true,
    "tier": "tier_1",
    "status": "active"
  },
  {
    "company_name": "Presight AI",
    "brand_name": "Presight",
    "slug": "presight-ai",
    "sector": "AI Analytics & Security Intelligence",
    "sub_sector": "Omni-Analytics & AI-Powered Surveillance",
    "hq_city": "Abu Dhabi",
    "hq_country": "UAE",
    "is_g42_group": true,
    "tier": "tier_1",
    "status": "active"
  },
  {
    "company_name": "Inception",
    "brand_name": null,
    "slug": "inception-g42",
    "sector": "AI Research & Models",
    "sub_sector": "Foundation Models & AI R&D",
    "hq_city": "Abu Dhabi",
    "hq_country": "UAE",
    "is_g42_group": true,
    "tier": "tier_1",
    "status": "active"
  },
  {
    "company_name": "Space42",
    "brand_name": null,
    "slug": "space42",
    "sector": "AI Space Intelligence",
    "sub_sector": "Satellite Intelligence & Geospatial AI",
    "hq_city": "Abu Dhabi",
    "hq_country": "UAE",
    "is_g42_group": true,
    "tier": "tier_1",
    "status": "active"
  },
  {
    "company_name": "M42",
    "brand_name": null,
    "slug": "m42-health",
    "sector": "AI Healthcare",
    "sub_sector": "Tech-Enabled Healthcare & Diagnostics",
    "hq_city": "Abu Dhabi",
    "hq_country": "UAE",
    "is_g42_group": true,
    "tier": "tier_1",
    "status": "active"
  },
  {
    "company_name": "Khazna Data Centers",
    "brand_name": "Khazna",
    "slug": "khazna-data-centers",
    "sector": "AI Infrastructure",
    "sub_sector": "Data Center & Cloud Infrastructure",
    "hq_city": "Abu Dhabi",
    "hq_country": "UAE",
    "is_g42_group": true,
    "tier": "tier_1",
    "status": "active"
  },
  {
    "company_name": "Astra Tech",
    "brand_name": null,
    "slug": "astra-tech",
    "sector": "AI Fintech & Identity",
    "sub_sector": "Digital Payments & Financial Super-App",
    "hq_city": "Abu Dhabi",
    "hq_country": "UAE",
    "is_g42_group": true,
    "tier": "tier_1",
    "status": "active"
  },
  {
    "company_name": "AIQ",
    "brand_name": null,
    "slug": "aiq-adnoc-g42",
    "sector": "AI Energy",
    "sub_sector": "AI for Oil & Gas Sector",
    "hq_city": "Abu Dhabi",
    "hq_country": "UAE",
    "is_g42_group": true,
    "tier": "tier_1",
    "status": "active"
  },
  {
    "company_name": "Katim",
    "brand_name": "Katim (Digital14)",
    "slug": "katim-digital14",
    "sector": "AI Cybersecurity",
    "sub_sector": "Secure Communications & Sovereign Tech",
    "hq_city": "Abu Dhabi",
    "hq_country": "UAE",
    "is_g42_group": true,
    "tier": "tier_1",
    "status": "active"
  },
  {
    "company_name": "Help AG",
    "brand_name": null,
    "slug": "help-ag",
    "sector": "AI Cybersecurity",
    "sub_sector": "Managed Security Services & Threat Intelligence",
    "hq_city": "Abu Dhabi",
    "hq_country": "UAE",
    "is_g42_group": false,
    "tier": "tier_1",
    "status": "active"
  },
  {
    "company_name": "Injazat",
    "brand_name": null,
    "slug": "injazat",
    "sector": "AI Cloud & Cybersecurity",
    "sub_sector": "Digital Transformation & Managed Security",
    "hq_city": "Abu Dhabi",
    "hq_country": "UAE",
    "is_g42_group": false,
    "tier": "tier_1",
    "status": "active"
  },
  {
    "company_name": "Axon Technologies",
    "brand_name": null,
    "slug": "axon-technologies",
    "sector": "AI Cybersecurity",
    "sub_sector": "Information Security & Threat Detection",
    "hq_city": "Abu Dhabi",
    "hq_country": "UAE",
    "is_g42_group": false,
    "tier": "tier_2",
    "status": "active"
  },
  {
    "company_name": "AHAD",
    "brand_name": null,
    "slug": "ahad-security",
    "sector": "AI Cybersecurity",
    "sub_sector": "Cyber Defense & Threat Intelligence",
    "hq_city": "Abu Dhabi",
    "hq_country": "UAE",
    "is_g42_group": false,
    "tier": "tier_2",
    "status": "active"
  },
  {
    "company_name": "DTS Solution",
    "brand_name": null,
    "slug": "dts-solution",
    "sector": "AI Cybersecurity",
    "sub_sector": "Technical Security Assessments & Managed Security",
    "hq_city": "Abu Dhabi",
    "hq_country": "UAE",
    "is_g42_group": false,
    "tier": "tier_2",
    "status": "active"
  },
  {
    "company_name": "Paramount Computer Systems",
    "brand_name": null,
    "slug": "paramount-computer-systems",
    "sector": "AI Cybersecurity",
    "sub_sector": "Zero Trust, IAM & SOC Solutions",
    "hq_city": "Abu Dhabi",
    "hq_country": "UAE",
    "is_g42_group": false,
    "tier": "tier_2",
    "status": "active"
  },
  {
    "company_name": "Microminder Cyber Security",
    "brand_name": "Microminder",
    "slug": "microminder-cybersecurity",
    "sector": "AI Cybersecurity",
    "sub_sector": "Penetration Testing & Cloud Security",
    "hq_city": "Abu Dhabi",
    "hq_country": "UAE",
    "is_g42_group": false,
    "tier": "tier_2",
    "status": "active"
  },
  {
    "company_name": "Cloud Box Technologies",
    "brand_name": null,
    "slug": "cloud-box-technologies",
    "sector": "AI Cloud & Cybersecurity",
    "sub_sector": "Cloud-Native Security & IT Managed Services",
    "hq_city": "Abu Dhabi",
    "hq_country": "UAE",
    "is_g42_group": false,
    "tier": "tier_2",
    "status": "active"
  },
  {
    "company_name": "Katim Secure Communications",
    "brand_name": "Katim",
    "slug": "katim-secure-comms",
    "sector": "AI Cybersecurity",
    "sub_sector": "Secure Mobile OS & Communications",
    "hq_city": "Abu Dhabi",
    "hq_country": "UAE",
    "is_g42_group": true,
    "tier": "tier_1",
    "status": "active"
  },
  {
    "company_name": "UAE Cyber Security Council",
    "brand_name": null,
    "slug": "uae-cybersecurity-council",
    "sector": "Government AI Security",
    "sub_sector": "National Cybersecurity Governance",
    "hq_city": "Abu Dhabi",
    "hq_country": "UAE",
    "is_g42_group": false,
    "tier": "tier_1",
    "status": "active"
  },
  {
    "company_name": "SmartTech247",
    "brand_name": null,
    "slug": "smarttech247-uae",
    "sector": "AI Cybersecurity",
    "sub_sector": "AI-Powered SOC & Threat Detection",
    "hq_city": "Abu Dhabi",
    "hq_country": "UAE",
    "is_g42_group": false,
    "tier": "tier_3",
    "status": "active"
  },
  {
    "company_name": "Omnix International",
    "brand_name": null,
    "slug": "omnix-international",
    "sector": "AI Security & Surveillance",
    "sub_sector": "Physical Security & AI Video Analytics",
    "hq_city": "Abu Dhabi",
    "hq_country": "UAE",
    "is_g42_group": false,
    "tier": "tier_2",
    "status": "active"
  },
  {
    "company_name": "Solutions+",
    "brand_name": null,
    "slug": "solutions-plus",
    "sector": "AI Enterprise Services",
    "sub_sector": "AI-Driven Shared Services & Implementation",
    "hq_city": "Abu Dhabi",
    "hq_country": "UAE",
    "is_g42_group": false,
    "tier": "tier_1",
    "status": "active"
  },
  {
    "company_name": "Mubadala Investment Company",
    "brand_name": "Mubadala",
    "slug": "mubadala",
    "sector": "Sovereign Investment & AI",
    "sub_sector": "Sovereign Wealth Fund & Technology Investor",
    "hq_city": "Abu Dhabi",
    "hq_country": "UAE",
    "is_g42_group": false,
    "tier": "tier_1",
    "status": "active"
  }
]